flxtrtwn_orderedset/__init__.py
flxtrtwn_orderedset/orderedset.py
flxtrtwn_orderedset-0.1.1.dist-info/METADATA
flxtrtwn_orderedset-0.1.1.dist-info/WHEEL
flxtrtwn_orderedset-0.1.1.dist-info/RECORD
